seal/__init__.py
seal/__main__.py
seal/analyze.py
seal/common.py
seal/config.py
seal/exceptions.py
seal/misc.py
seal/plot.py
seal/preprocess.py
seal/py.typed
seal_tool-0.11.0.dist-info/LICENSE
seal_tool-0.11.0.dist-info/METADATA
seal_tool-0.11.0.dist-info/WHEEL
seal_tool-0.11.0.dist-info/entry_points.txt
seal_tool-0.11.0.dist-info/top_level.txt
seal_tool-0.11.0.dist-info/RECORD
