Metadata-Version: 2.1
Name: seal-tool
Version: 0.11.0
Summary: A tool to perform richness-extent-grain analyses
Author-email: Martin Matouš <m@matous.dev>, Barbora Winterová <winterova@mail.muni.cz>
License: GNU GENERAL PUBLIC LICENSE
Project-URL: Homepage, https://codeberg.org/mmatous/seal
Project-URL: Bug Tracker, https://codeberg.org/mmatous/seal/issues
Keywords: area,distance decay,ecology,extent,grain,richness,SAR,scale,species,species-area
Classifier: Development Status :: 5 - Production/Stable
Classifier: Environment :: Console
Classifier: Intended Audience :: Science/Research
Classifier: License :: OSI Approved :: GNU General Public License v3 (GPLv3)
Classifier: Natural Language :: English
Classifier: Programming Language :: Python :: 3
Classifier: Operating System :: OS Independent
Classifier: Topic :: Scientific/Engineering
Requires-Python: >=3.12
License-File: LICENSE
Requires-Dist: alive-progress ~=3.1
Requires-Dist: numba ~=0.59
Requires-Dist: numexpr ~=2.9
Requires-Dist: pandas ~=2.2
Requires-Dist: pydantic ~=2.6
Requires-Dist: scipy ~=1.12
Requires-Dist: seaborn ~=0.13.2
Provides-Extra: alt_plot
Requires-Dist: plotly ; extra == 'alt_plot'
Provides-Extra: dev
Requires-Dist: mypy ==1.9 ; extra == 'dev'
Requires-Dist: pandas-stubs ~=2.2 ; extra == 'dev'
Requires-Dist: pytest ~=8.1 ; extra == 'dev'
Requires-Dist: pytest-cov ~=5.0 ; extra == 'dev'
Requires-Dist: ruff ==0.3.4 ; extra == 'dev'
